internet_ml/Audio/__init__.py
internet_ml/Image/__init__.py
internet_ml/NLP/README.md
internet_ml/NLP/__init__.py
internet_ml/NLP/context/__init__.py
internet_ml/NLP/no_context/QA.py
internet_ml/NLP/no_context/__init__.py
internet_ml/README.md
internet_ml/__init__.py
internet_ml/__main__.py
internet_ml/tools/ChatGPT.py
internet_ml/tools/NLP/__init__.py
internet_ml/tools/NLP/data/__init__.py
internet_ml/tools/NLP/data/adremover.py
internet_ml/tools/NLP/data/database.py
internet_ml/tools/NLP/data/internet.py
internet_ml/tools/NLP/entity_recognition.py
internet_ml/tools/NLP/keywords.py
internet_ml/tools/NLP/ml/__init__.py
internet_ml/tools/NLP/ml/dataset/README.md
internet_ml/tools/NLP/ml/dataset/__init__.py
internet_ml/tools/NLP/ml/dataset/long_QA.py
internet_ml/tools/NLP/ml/long_QA.py
internet_ml/tools/NLP/ml/nli.py
internet_ml/tools/NLP/ml/question_converter.py
internet_ml/tools/NLP/ml/summarize.py
internet_ml/tools/NLP/ml/training/__init__.py
internet_ml/tools/NLP/ml/training/gpt-neox-20b-quac.py
internet_ml/tools/NLP/normalize.py
internet_ml/tools/NLP/pos_tagging.py
internet_ml/tools/NLP/relevancy.py
internet_ml/tools/NLP/sentencize.py
internet_ml/tools/__init__.py
internet_ml/utils/NLP/__init__.py
internet_ml/utils/NLP/constants.py
internet_ml/utils/__init__.py
internet_ml/utils/config.py
internet_ml-3.1.0.dist-info/LICENSE
internet_ml-3.1.0.dist-info/WHEEL
internet_ml-3.1.0.dist-info/entry_points.txt
internet_ml-3.1.0.dist-info/METADATA
internet_ml-3.1.0.dist-info/RECORD
