Metadata-Version: 2.1
Name: internet-ml
Version: 3.1.0
Summary: Internet-ML: Allowing ML to connect to the internet
Home-page: https://github.com/thamognya/internet-ml
License: AGPL-3.0-or-later
Keywords: Transformer,NLP,NLI,Internet,Networks,BERT,SOTA,XLNet,sentence,embedding,PyTorch,NLP,deep,learning,Tensorflow,Huggingface,image-gen,dall-E,gpt,stable diffusion
Author: Thamognya Kodi
Author-email: contact@thamognya.com
Requires-Python: >=3.9,<4.0
Classifier: Development Status :: 3 - Alpha
Classifier: Intended Audience :: Science/Research
Classifier: License :: OSI Approved :: GNU Affero General Public License v3 or later (AGPLv3+)
Classifier: Operating System :: OS Independent
Classifier: Programming Language :: Python :: 3
Classifier: Programming Language :: Python :: 3.9
Classifier: Programming Language :: Python :: 3.10
Classifier: Programming Language :: Python :: 3.11
Classifier: Programming Language :: Python :: 3
Classifier: Programming Language :: Python :: 3.11
Classifier: Topic :: Scientific/Engineering :: Artificial Intelligence
Requires-Dist: accelerate (>=0.15.0,<0.16.0)
Requires-Dist: beautifulsoup4 (>=4.11.1,<5.0.0)
Requires-Dist: contractions (>=0.1.73,<0.2.0)
Requires-Dist: cssselect (>=1.2.0,<2.0.0)
Requires-Dist: datasets (>=2.8.0,<3.0.0)
Requires-Dist: diffusers (>=0.11.1,<0.12.0)
Requires-Dist: huggingface-hub (>=0.11.1,<0.12.0)
Requires-Dist: lxml (>=4.9.2,<5.0.0)
Requires-Dist: nltk (>=3.8,<4.0)
Requires-Dist: numpy (>=1.24.0,<2.0.0)
Requires-Dist: openai (>=0.26.0,<0.27.0)
Requires-Dist: pandas (>=1.5.2,<2.0.0)
Requires-Dist: python-dotenv (>=0.21.0,<0.22.0)
Requires-Dist: requests (>=2.28.1,<3.0.0)
Requires-Dist: revchatgpt (>=0.1.1,<0.2.0)
Requires-Dist: rich (>=10.14,<14.0)
Requires-Dist: scikit-learn (>=1.2.0,<2.0.0)
Requires-Dist: spacy (>=3.4.4,<4.0.0)
Requires-Dist: timm (>=0.6.12,<0.7.0)
Requires-Dist: tokenizers (>=0.13.2,<0.14.0)
Requires-Dist: torch (>=1.13.1,<2.0.0)
Requires-Dist: torchaudio (>=0.13.1,<0.14.0)
Requires-Dist: torchvision (>=0.14.1,<0.15.0)
Requires-Dist: typer[all] (>=0.4.0,<0.5.0)
Requires-Dist: types-requests (>=2.28.11.7,<3.0.0.0)
Requires-Dist: urlextract (>=1.8.0,<2.0.0)
Project-URL: Repository, https://github.com/thamognya/internet-ml
